linumpy/__init__.py
linumpy/io/__init__.py
linumpy/io/allen.py
linumpy-0.1.1.data/scripts/linum_download_allen.py
linumpy-0.1.1.dist-info/LICENSE
linumpy-0.1.1.dist-info/METADATA
linumpy-0.1.1.dist-info/WHEEL
linumpy-0.1.1.dist-info/top_level.txt
linumpy-0.1.1.dist-info/RECORD
