Metadata-Version: 2.1
Name: linumpy
Version: 0.1.1
Summary: linumpy: microscopy tools and utilities
Home-page: https://github.com/linum-uqam/linumpy
Download-URL: 
Author: The LINUM developers
Author-email: 
Maintainer: Joël Lefebvre
Maintainer-email: lefebvre.joel@uqam.ca
License: GPLv3+
Platform: OS Independent
Classifier: Development Status :: 1 - Planning
Classifier: Environment :: Console
Classifier: Intended Audience :: Science/Research
Classifier: Operating System :: OS Independent
Classifier: Programming Language :: Python
Classifier: Topic :: Scientific/Engineering
Requires-Python: >=3.10
License-File: LICENSE
Requires-Dist: allensdk (==2.15.1)
Requires-Dist: nibabel (==5.1.0)
Requires-Dist: numpy (==1.24.3)
Requires-Dist: scipy (==1.10.1)
Requires-Dist: SimpleITK (==2.2.1)
